calendarius
